ZhecaishiXiyinliFaze/Dockerfile
ZhecaishiXiyinliFaze/README.md
ZhecaishiXiyinliFaze/__init__.py
ZhecaishiXiyinliFaze/__main__.py
ZhecaishiXiyinliFaze/file.epub
ZhecaishiXiyinliFaze/index.html
ZhecaishiXiyinliFaze/css/__init__.py
ZhecaishiXiyinliFaze/css/annotations.css
ZhecaishiXiyinliFaze/css/main.css
ZhecaishiXiyinliFaze/css/normalize.css
ZhecaishiXiyinliFaze/css/popup.css
ZhecaishiXiyinliFaze/font/__init__.py
ZhecaishiXiyinliFaze/font/fontello.eot
ZhecaishiXiyinliFaze/font/fontello.svg
ZhecaishiXiyinliFaze/font/fontello.ttf
ZhecaishiXiyinliFaze/font/fontello.woff
ZhecaishiXiyinliFaze/img/__init__.py
ZhecaishiXiyinliFaze/img/annotator-glyph-sprite.png
ZhecaishiXiyinliFaze/img/annotator-icon-sprite.png
ZhecaishiXiyinliFaze/img/apple-touch-icon.png
ZhecaishiXiyinliFaze/img/cancelfullscreen.png
ZhecaishiXiyinliFaze/img/close.png
ZhecaishiXiyinliFaze/img/fullscreen.png
ZhecaishiXiyinliFaze/img/loader.gif
ZhecaishiXiyinliFaze/img/menu-icon.png
ZhecaishiXiyinliFaze/img/save.png
ZhecaishiXiyinliFaze/img/saved.png
ZhecaishiXiyinliFaze/img/settings-s.png
ZhecaishiXiyinliFaze/img/settings.png
ZhecaishiXiyinliFaze/img/star.png
ZhecaishiXiyinliFaze/js/__init__.py
ZhecaishiXiyinliFaze/js/epub.js
ZhecaishiXiyinliFaze/js/epub.min.js
ZhecaishiXiyinliFaze/js/epub.min.map
ZhecaishiXiyinliFaze/js/hooks.min.js
ZhecaishiXiyinliFaze/js/hooks.min.map
ZhecaishiXiyinliFaze/js/reader.js
ZhecaishiXiyinliFaze/js/reader.js.map
ZhecaishiXiyinliFaze/js/reader.min.js
ZhecaishiXiyinliFaze/js/reader.min.map
ZhecaishiXiyinliFaze/js/hooks/__init__.py
ZhecaishiXiyinliFaze/js/hooks/extensions/__init__.py
ZhecaishiXiyinliFaze/js/hooks/extensions/highlight.js
ZhecaishiXiyinliFaze/js/libs/__init__.py
ZhecaishiXiyinliFaze/js/libs/jquery.min.js
ZhecaishiXiyinliFaze/js/libs/localforage.min.js
ZhecaishiXiyinliFaze/js/libs/screenfull.js
ZhecaishiXiyinliFaze/js/libs/screenfull.min.js
ZhecaishiXiyinliFaze/js/libs/zip.min.js
ZhecaishiXiyinliFaze/js/plugins/__init__.py
zhecaishi_xiyinli_faze-2022.10.7.1.dist-info/METADATA
zhecaishi_xiyinli_faze-2022.10.7.1.dist-info/WHEEL
zhecaishi_xiyinli_faze-2022.10.7.1.dist-info/entry_points.txt
zhecaishi_xiyinli_faze-2022.10.7.1.dist-info/top_level.txt
zhecaishi_xiyinli_faze-2022.10.7.1.dist-info/RECORD
